sbom/__init__.py
sbom/__main__.py
sbom/baseline.py
sbom/cli.py
sbom/consume.py
sbom/crypto.py
sbom/extension.py
sbom/fuzz.py
sbom/merge.py
sbom/mock.py
sbom/policy.py
sbom/produce.py
sbom/report.py
sbom/rule.py
sbom/sbom.py
sbom/transform.py
sbom-2023.10.7.dist-info/LICENSE
sbom-2023.10.7.dist-info/METADATA
sbom-2023.10.7.dist-info/WHEEL
sbom-2023.10.7.dist-info/entry_points.txt
sbom-2023.10.7.dist-info/top_level.txt
sbom-2023.10.7.dist-info/RECORD
