Metadata-Version: 2.1
Name: sbom
Version: 2023.10.7
Summary: Tree shaking for the minimal viable SBOM.
Author-email: Stefan Hagen <stefan@hagen.link>
Maintainer-email: Stefan Hagen <stefan@hagen.link>
Project-URL: Homepage, https://git.sr.ht/~sthagen/sbom
Project-URL: Bug-Tracker, https://todo.sr.ht/~sthagen/sbom
Project-URL: Documentation, https://codes.dilettant.life/docs/sbom
Project-URL: Source-Code, https://git.sr.ht/~sthagen/sbom
Project-URL: Test-Coverage, https://codes.dilettant.life/coverage/sbom
Keywords: baseline,cyclonedx,developer-tools,extension,software-bill-of-materials,spdx,validation
Classifier: Development Status :: 3 - Alpha
Classifier: Intended Audience :: Developers
Classifier: License :: OSI Approved :: MIT License
Classifier: Programming Language :: Python :: 3.10
Classifier: Programming Language :: Python :: 3.11
Classifier: Programming Language :: Python :: 3.12
Classifier: Programming Language :: Python :: 3.9
Classifier: Topic :: Software Development :: Build Tools
Requires-Python: >=3.9
License-File: LICENSE
Requires-Dist: attrs >=23.1.0
Requires-Dist: cyclonedx-bom >=3.11.2
Requires-Dist: jsonschema >=4.19.1
Requires-Dist: referencing >=0.30.2
Requires-Dist: spdx-tools >=0.8.1
Requires-Dist: typer >=0.9.0
Requires-Dist: xmlschema >=2.5.0
Provides-Extra: dev
Requires-Dist: black ; extra == 'dev'
Requires-Dist: coverage ; extra == 'dev'
Requires-Dist: hypothesis ; extra == 'dev'
Requires-Dist: mypy ; extra == 'dev'
Requires-Dist: pytest ; extra == 'dev'
Requires-Dist: pytest-cov ; extra == 'dev'
Requires-Dist: pytest-flake8 ; extra == 'dev'
Requires-Dist: ruff ; extra == 'dev'
